{
    "1": [
        1,
        "Maria",
        "Design"
    ],
    "3": [
        3,
        "Viviane",
        "Eletricista"
    ],
    "4": [
        4,
        "Aurora",
        "Arquiteta"
    ],
    "5": [
        5,
        "Oliver",
        "Director"
    ],
    "6": [
        6,
        "Amanda",
        "Lutadora"
    ],
    "7": [
        7,
        "Geyse",
        "Engenheira"
    ],
    "8": [
        8,
        "Joab",
        "Professor"
    ],
    "9": [
        9,
        "Bernardo",
        "Streamer"
    ]
}